[
    {
        "nombre": "",
        "talla": "",
        "precio": "***€",
        "imagenURL": "Productos/72.jpg",
        "url":"#"
    },
    {
        "nombre": "",
        "talla": "",
        "precio": "***€",
        "imagenURL": "Productos/73.jpg",
        "url":"#"
    },
    {
        "nombre": "",
        "talla": "",
        "precio": "***€",
        "imagenURL": "Productos/74.jpg",
        "url":"#"
    },
    {
        "nombre": "",
        "talla": "",
        "precio": "***€",
        "imagenURL": "Productos/75.jpg",
        "url":"#"
    },
    {
        "nombre": "",
        "talla": "",
        "precio": "***€",
        "imagenURL": "Productos/76.jpg",
        "url":"#"
    },
    {
        "nombre": "",
        "talla": "",
        "precio": "***€",
        "imagenURL": "Productos/77.jpg",
        "url":"#"
    },
    {
        "nombre": "",
        "talla": "",
        "precio": "***€",
        "imagenURL": "Productos/78.jpg",
        "url":"#"
    },
    {
        "nombre": "",
        "talla": "",
        "precio": "***€",
        "imagenURL": "Productos/79.jpg",
        "url":"#"
    },
    {
        "nombre": "",
        "talla": "",
        "precio": "***€",
        "imagenURL": "Productos/80.jpg",
        "url":"#"
    },
    {
        "nombre": "",
        "talla": "",
        "precio": "***€",
        "imagenURL": "Productos/81.jpg",
        "url":"#"
    },
    {
        "nombre": "",
        "talla": "",
        "precio": "***€",
        "imagenURL": "Productos/82.jpg",
        "url":"#"
    },
    {
        "nombre": "",
        "talla": "",
        "precio": "***€",
        "imagenURL": "Productos/83.jpg",
        "url":"#"
    },
    {
        "nombre": "",
        "talla": "",
        "precio": "***€",
        "imagenURL": "Productos/84.jpg",
        "url":"#"
    },
    {
        "nombre": "",
        "talla": "",
        "precio": "***€",
        "imagenURL": "Productos/85.jpg",
        "url":"#"
    },
    {
        "nombre": "",
        "talla": "",
        "precio": "***€",
        "imagenURL": "Productos/86.jpg",
        "url":"#"
    },
    {
        "nombre": "",
        "talla": "",
        "precio": "***€",
        "imagenURL": "Productos/87.jpg",
        "url":"#"
    },
    {
        "nombre": "",
        "talla": "",
        "precio": "***€",
        "imagenURL": "Productos/88.jpg",
        "url":"#"
    },
    {
        "nombre": "",
        "talla": "",
        "precio": "***€",
        "imagenURL": "Productos/89.jpg",
        "url":"#"
    },
    {
        "nombre": "",
        "talla": "",
        "precio": "***€",
        "imagenURL": "Productos/90.jpg",
        "url":"#"
    },
    {
        "nombre": "",
        "talla": "",
        "precio": "***€",
        "imagenURL": "Productos/91.jpg",
        "url":"#"
    },
    {
        "nombre": "",
        "talla": "",
        "precio": "***€",
        "imagenURL": "Productos/92.jpg",
        "url":"#"
    },
    {
        "nombre": "",
        "talla": "",
        "precio": "***€",
        "imagenURL": "Productos/93.jpg",
        "url":"#"
    },
    {
        "nombre": "",
        "talla": "",
        "precio": "***€",
        "imagenURL": "Productos/94.jpg",
        "url":"#"
    },
    {
        "nombre": "",
        "talla": "",
        "precio": "***€",
        "imagenURL": "Productos/95.jpg",
        "url":"#"
    },
    {
        "nombre": "",
        "talla": "",
        "precio": "***€",
        "imagenURL": "Productos/96.jpg",
        "url":"#"
    },
    {
        "nombre": "",
        "talla": "",
        "precio": "***€",
        "imagenURL": "Productos/97.jpg",
        "url":"#"
    },
    {
        "nombre": "",
        "talla": "",
        "precio": "***€",
        "imagenURL": "Productos/98.jpg",
        "url":"#"
    },
    {
        "nombre": "",
        "talla": "",
        "precio": "***€",
        "imagenURL": "Productos/99.jpg",
        "url":"#"
    },
    {
        "nombre": "",
        "talla": "",
        "precio": "***€",
        "imagenURL": "Productos/100.jpg",
        "url":"#"
    },
    {
        "nombre": "",
        "talla": "",
        "precio": "***€",
        "imagenURL": "Productos/101.jpg",
        "url":"#"
    },
    {
        "nombre": "",
        "talla": "",
        "precio": "***€",
        "imagenURL": "Productos/102.jpg",
        "url":"#"
    },
    {
        "nombre": "",
        "talla": "",
        "precio": "***€",
        "imagenURL": "Productos/103.jpg",
        "url":"#"
    },
    {
        "nombre": "",
        "talla": "",
        "precio": "***€",
        "imagenURL": "Productos/104.jpg",
        "url":"#"
    },
    {
        "nombre": "",
        "talla": "",
        "precio": "***€",
        "imagenURL": "Productos/105.jpg",
        "url":"#"
    },
    {
        "nombre": "",
        "talla": "",
        "precio": "***€",
        "imagenURL": "Productos/106.jpg",
        "url":"#"
    },
    {
        "nombre": "",
        "talla": "",
        "precio": "***€",
        "imagenURL": "Productos/107.jpg",
        "url":"#"
    },
    {
        "nombre": "",
        "talla": "",
        "precio": "***€",
        "imagenURL": "Productos/108.jpg",
        "url":"#"
    },
    {
        "nombre": "",
        "talla": "",
        "precio": "***€",
        "imagenURL": "Productos/109.jpg",
        "url":"#"
    },
    {
        "nombre": "",
        "talla": "",
        "precio": "***€",
        "imagenURL": "Productos/110.jpg",
        "url":"#"
    },
    {
        "nombre": "",
        "talla": "",
        "precio": "***€",
        "imagenURL": "Productos/111.jpg",
        "url":"#"
    },
    {
        "nombre": "",
        "talla": "",
        "precio": "***€",
        "imagenURL": "Productos/112.jpg",
        "url":"#"
    },
    {
        "nombre": "",
        "talla": "",
        "precio": "***€",
        "imagenURL": "Productos/113.jpg",
        "url":"#"
    }
]